{
  "name": "Lab01-OfficeHours-Logger",
  "nodes": [
    {
      "parameters": {
        "rule": {
          "interval": [
            {
              "field": "weeks",
              "triggerAtDay": [
                1,
                2,
                3,
                4,
                5
              ],
              "triggerAtHour": 9
            }
          ]
        }
      },
      "type": "n8n-nodes-base.scheduleTrigger",
      "typeVersion": 1.3,
      "position": [
        -160,
        -32
      ],
      "id": "30f76248-bdb6-47e3-bbcf-710f7c8ab9c0",
      "name": "Schedule Trigger"
    },
    {
      "parameters": {
        "url": "https://zenquotes.io/api/random",
        "options": {
          "allowUnauthorizedCerts": true,
          "response": {
            "response": {
              "responseFormat": "json"
            }
          }
        }
      },
      "type": "n8n-nodes-base.httpRequest",
      "typeVersion": 4.4,
      "position": [
        80,
        -16
      ],
      "id": "5c811462-3103-4c20-aba0-ce21aec5beb4",
      "name": "HTTP Request"
    },
    {
      "parameters": {
        "assignments": {
          "assignments": [
            {
              "id": "8bed30a3-6bb9-488a-81d9-40c193e43f3f",
              "name": "quote",
              "value": "={{$json.content}}",
              "type": "string"
            },
            {
              "id": "3f940c2c-3369-493b-a805-6c708c0f0325",
              "name": "author",
              "value": "={{$json.author}}",
              "type": "string"
            },
            {
              "id": "aee66d6a-17a6-4818-a259-19d529c41564",
              "name": "loggedAt",
              "value": "={{$now}}",
              "type": "string"
            }
          ]
        },
        "options": {}
      },
      "type": "n8n-nodes-base.set",
      "typeVersion": 3.4,
      "position": [
        288,
        -32
      ],
      "id": "da46003c-0b66-4ae5-821b-2899b3b49dbc",
      "name": "Edit Fields"
    },
    {
      "parameters": {
        "operation": "write",
        "fileName": "/tmp/quotes.txt",
        "options": {
          "append": true
        }
      },
      "type": "n8n-nodes-base.readWriteFile",
      "typeVersion": 1.1,
      "position": [
        736,
        80
      ],
      "id": "e8738e89-f323-42cd-b929-e942a891a93a",
      "name": "Read/Write Files from Disk"
    },
    {
      "parameters": {
        "operation": "toText",
        "sourceProperty": "author",
        "options": {}
      },
      "type": "n8n-nodes-base.convertToFile",
      "typeVersion": 1.1,
      "position": [
        576,
        80
      ],
      "id": "f7bbc5ec-9186-4ea3-b617-29cb57273ca4",
      "name": "Convert to File"
    },
    {
      "parameters": {
        "conditions": {
          "options": {
            "caseSensitive": true,
            "leftValue": "",
            "typeValidation": "loose",
            "version": 3
          },
          "conditions": [
            {
              "id": "3dd3841f-9b69-4fde-ba48-4faf5954bc72",
              "leftValue": "=   {{ new Date().getHours() }}",
              "rightValue": 9,
              "operator": {
                "type": "number",
                "operation": "gte"
              }
            },
            {
              "id": "d0af6257-56a4-4627-8d72-5596a1c1a8d9",
              "leftValue": "={{ new Date().getHours() }}",
              "rightValue": 17,
              "operator": {
                "type": "number",
                "operation": "lt"
              }
            }
          ],
          "combinator": "and"
        },
        "looseTypeValidation": true,
        "options": {}
      },
      "type": "n8n-nodes-base.if",
      "typeVersion": 2.3,
      "position": [
        240,
        176
      ],
      "id": "8a0ceede-a806-4379-837f-8af82e5a9836",
      "name": "If"
    },
    {
      "parameters": {
        "operation": "toText",
        "sourceProperty": "  Skipped (outside office hours)",
        "options": {}
      },
      "type": "n8n-nodes-base.convertToFile",
      "typeVersion": 1.1,
      "position": [
        432,
        272
      ],
      "id": "71e64964-65ab-4c48-9cfa-6074847aadee",
      "name": "Convert to File1"
    },
    {
      "parameters": {
        "operation": "write",
        "fileName": "/tmp/skipped.txt",
        "options": {
          "append": true
        }
      },
      "type": "n8n-nodes-base.readWriteFile",
      "typeVersion": 1.1,
      "position": [
        640,
        272
      ],
      "id": "1e08091d-090b-4655-9ba4-c3ebb5d6fb14",
      "name": "Read/Write Files from Disk1"
    }
  ],
  "pinData": {},
  "connections": {
    "Edit Fields": {
      "main": [
        [
          {
            "node": "If",
            "type": "main",
            "index": 0
          }
        ]
      ]
    },
    "Schedule Trigger": {
      "main": [
        [
          {
            "node": "HTTP Request",
            "type": "main",
            "index": 0
          }
        ]
      ]
    },
    "HTTP Request": {
      "main": [
        [
          {
            "node": "Edit Fields",
            "type": "main",
            "index": 0
          }
        ]
      ]
    },
    "Convert to File": {
      "main": [
        [
          {
            "node": "Read/Write Files from Disk",
            "type": "main",
            "index": 0
          }
        ]
      ]
    },
    "If": {
      "main": [
        [
          {
            "node": "Convert to File",
            "type": "main",
            "index": 0
          }
        ],
        [
          {
            "node": "Convert to File1",
            "type": "main",
            "index": 0
          }
        ]
      ]
    },
    "Read/Write Files from Disk": {
      "main": [
        []
      ]
    },
    "Convert to File1": {
      "main": [
        [
          {
            "node": "Read/Write Files from Disk1",
            "type": "main",
            "index": 0
          }
        ]
      ]
    }
  },
  "active": false,
  "settings": {
    "executionOrder": "v1",
    "binaryMode": "separate",
    "availableInMCP": false
  },
  "versionId": "f159214a-8d09-4e61-bf66-2c2674e31c2d",
  "meta": {
    "instanceId": "e83ed361eedfb0eeb5f03175381132386c665b0e477bdc5ef60a598901123177"
  },
  "id": "XC1GPTXrH84oCnAG",
  "tags": []
}